<?xml version="1.0" encoding="UTF-8" ?>
<!DOCTYPE mapper
        PUBLIC "-//mybatis.org//DTD Mapper 3.0//EN"
        "https://mybatis.org/dtd/mybatis-3-mapper.dtd">
<mapper namespace="com.example.project_machimo.auction.dao.ProductsDAO">
    <update id="succeedsSale">

        UPDATE PRODUCTS
        SET p_sales_status =3
        where P_DUR  <![CDATA[<=]]>  #{param1} AND PRODUCT_id = #{param2}

    </update>
    <update id="failedSale">
        UPDATE PRODUCTS
        SET p_sales_status =5
        where P_DUR  <![CDATA[<=]]>  #{param1} AND PRODUCT_id = #{param2}
    </update>
    <update id="updatePrice">
        UPDATE PRODUCTS p
        SET P_DIRECT = (
        SELECT a.HIGHEST_BID
        FROM AUCTIONS a
        WHERE p.PRODUCT_ID = a.PRODUCTS_ID and p.P_SALES_STATUS = 3
        )
        WHERE EXISTS (
        SELECT 1
        FROM AUCTIONS a
        WHERE p.PRODUCT_ID = a.PRODUCTS_ID and p.P_SALES_STATUS = 3
        )
    </update>
    <update id="updateProductStatusCompletedCase">
        update PRODUCTS set P_SALES_STATUS = 2
        where PRODUCT_ID = #{param1}
    </update>
    <update id="updateLikeUp">
        update PRODUCTS set P_LIKE = P_LIKE + 1
        where PRODUCT_ID = #{0}
    </update>
    <update id="updateLikeDown">
        update PRODUCTS set P_LIKE = P_LIKE - 1
        where PRODUCT_ID = #{0}
    </update>
    <update id="updateHit">update PRODUCTS set p_hit= p_hit +1
        where PRODUCT_ID = #{param1}
    </update>
    <select id="pList" resultType="com.example.project_machimo.auction.dto.ProductsVO">
        select * from products
    </select>
    <select id="pView" resultType="com.example.project_machimo.auction.dto.ProductsVO">
        select * from products where product_id = #{0}
    </select>


</mapper>

